hanifx-24.0.0.dist-info/licenses/LICENSE
hanifx_secure_encode/__init__.py
hanifx_secure_encode/encoder.py
hanifx_secure_encode/key_manager.py
hanifx_secure_encode/metadata.py
hanifx_secure_encode/warning_system.py
hanifx-24.0.0.dist-info/METADATA
hanifx-24.0.0.dist-info/WHEEL
hanifx-24.0.0.dist-info/top_level.txt
hanifx-24.0.0.dist-info/RECORD
