Metadata-Version: 2.4
Name: hanifx
Version: 24.0.0
Summary: Hanifx Secure Encoding Module for text and files
Home-page: https://pypi.org/project/hanifx/
Author: Hanif
Author-email: sajim4653@gmail.com
Classifier: Programming Language :: Python :: 3
Classifier: License :: OSI Approved :: MIT License
Classifier: Operating System :: OS Independent
Classifier: Topic :: Security
Classifier: Intended Audience :: Developers
Requires-Python: >=3.6
License-File: LICENSE
Dynamic: author
Dynamic: author-email
Dynamic: classifier
Dynamic: description
Dynamic: description-content-type
Dynamic: home-page
Dynamic: license-file
Dynamic: requires-python
Dynamic: summary
